polypip/__init__.py
polypip/polypip.py
polypip/stdlib
polypip-0.0.9.dist-info/LICENSE
polypip-0.0.9.dist-info/METADATA
polypip-0.0.9.dist-info/WHEEL
polypip-0.0.9.dist-info/entry_points.txt
polypip-0.0.9.dist-info/top_level.txt
polypip-0.0.9.dist-info/RECORD
