Metadata-Version: 2.1
Name: polypip
Version: 0.0.9
Summary: A lightweight python module designed to generate a requirements file for your project.
Author-email: Alexander Crayton <alexppeltier@gmail.com>, Parker Spaan <parkerspaan@yahoo.com>
License: Apache License
Project-URL: repository, https://github.com/admeeer/polypip
Keywords: requirements file,imports
Classifier: Intended Audience :: Developers
Classifier: License :: OSI Approved :: Apache Software License
Classifier: Programming Language :: Python :: 3
Requires-Python: >=3.9
License-File: LICENSE
